orloclient/__init__.py
orloclient/__init__.pyc
orloclient/__main__.py
orloclient/__main__.pyc
orloclient/_requests.py
orloclient/base_client.py
orloclient/base_client.pyc
orloclient/client.py
orloclient/client.pyc
orloclient/config.py
orloclient/config.pyc
orloclient/exceptions.py
orloclient/exceptions.pyc
orloclient/mock_orlo.py
orloclient/mock_orlo.pyc
orloclient/objects.py
orloclient/objects.pyc
orloclient-0.4.5.dist-info/DESCRIPTION.rst
orloclient-0.4.5.dist-info/METADATA
orloclient-0.4.5.dist-info/RECORD
orloclient-0.4.5.dist-info/WHEEL
orloclient-0.4.5.dist-info/entry_points.txt
orloclient-0.4.5.dist-info/metadata.json
orloclient-0.4.5.dist-info/top_level.txt
tests/__init__.py
tests/test_command_line.py
tests/test_integration.py
tests/test_mock.py
tests/test_orloclient.py
tests/test_package.py
tests/test_release.py
