Metadata-Version: 2.0
Name: orloclient
Version: 0.4.5
Summary: Client to the Orlo deployment _data capture API
Home-page: https://github.com/eBayClassifiedsGroup/orloclient
Author: Alex Forbes
Author-email: alforbes@ebay.com
License: GPL
Platform: UNKNOWN
Requires-Dist: arrow
Requires-Dist: requests
Provides-Extra: install
Requires-Dist: arrow; extra == 'install'
Requires-Dist: requests; extra == 'install'
Provides-Extra: test
Requires-Dist: Flask-Testing; extra == 'test'
Requires-Dist: httpretty; extra == 'test'
Requires-Dist: orlo (>=0.4.0); extra == 'test'
Requires-Dist: pytest; extra == 'test'
Requires-Dist: mock; extra == 'test'
